<?xml version="1.0" encoding="UTF-8"?>
<Medication xmlns="http://hl7.org/fhir">
    <id value="DGUV-ENLA-Bsp-MedikationArzneimittel" />
    <meta>
        <profile value="http://fhir.dguv.de/ENLA/Medication/DGUV-ENLA-PR-MedikationArzneimittel" />
    </meta>
      <code>
        <coding>
            <system value="http://fhir.de/CodeSystem/ifa/pzn" />
            <code value="04823572" />
        </coding>
        <text value="ACC long 600mg" />
      </code>
      <status value="active"/>
      <manufacturer>
        <display value="Hexal AG"/>     
      </manufacturer>
      <form>
        <coding>
          <system value="https://fhir.kbv.de/CodeSystem/KBV_CS_SFHIR_KBV_DARREICHUNGSFORM" />
          <version value="1.15"/>
          <code value="BTA"/>
          <display value="Brausetabletten"/>
        </coding>
      </form>
      <batch>
        <lotNumber value="1234"/>
      </batch>
</Medication>